odoo8_addon_import_odbc-8.0.0.1.3-py2.7-nspkg.pth
odoo_addons/import_odbc/import_odbc_demo.xml
odoo_addons/import_odbc/__openerp__.py
odoo_addons/import_odbc/import_odbc.py
odoo_addons/import_odbc/__init__.py
odoo_addons/import_odbc/import_odbc_view.xml
odoo_addons/import_odbc/README.rst
odoo_addons/import_odbc/security/ir.model.access.csv
odoo_addons/import_odbc/images/snapshot2.png
odoo_addons/import_odbc/images/snapshot1.png
odoo_addons/import_odbc/static/description/icon.png
odoo8_addon_import_odbc-8.0.0.1.3.dist-info/top_level.txt
odoo8_addon_import_odbc-8.0.0.1.3.dist-info/WHEEL
odoo8_addon_import_odbc-8.0.0.1.3.dist-info/RECORD
odoo8_addon_import_odbc-8.0.0.1.3.dist-info/metadata.json
odoo8_addon_import_odbc-8.0.0.1.3.dist-info/DESCRIPTION.rst
odoo8_addon_import_odbc-8.0.0.1.3.dist-info/METADATA
odoo8_addon_import_odbc-8.0.0.1.3.dist-info/namespace_packages.txt
