Metadata-Version: 2.0
Name: odoo8-addon-import-odbc
Version: 8.0.0.1.3
Summary: Import data from SQL and ODBC data sources.
Home-page: http://launchpad.net/addons-tko
Author: Daniel Reis,Odoo Community Association (OCA)
Author-email: support@odoo-community.org
License: AGPL-3
Platform: UNKNOWN
Requires-Dist: odoo (<9.0a,>=8.0a)
Requires-Dist: odoo8-addon-base-external-dbsource
Classifier: Programming Language :: Python :: 2.7
Classifier: Framework :: Odoo
Classifier: License :: OSI Approved :: GNU Affero General Public License v3
